rooms_shared_services/__init__.py
rooms_shared_services/src/__init__.py
rooms_shared_services/src/delayed_tasks/abstract.py
rooms_shared_services/src/delayed_tasks/models.py
rooms_shared_services/src/delayed_tasks/processor.py
rooms_shared_services/src/delayed_tasks/runner.py
rooms_shared_services/src/delayed_tasks/sandbox.py
rooms_shared_services/src/delayed_tasks/storage.py
rooms_shared_services/src/delayed_tasks/tracker.py
rooms_shared_services/src/encoders/json.py
rooms_shared_services/src/exceptions/storage.py
rooms_shared_services/src/fakers/fake.py
rooms_shared_services/src/lambda_handlers/abstract/callbacks.py
rooms_shared_services/src/lambda_handlers/abstract/handlers.py
rooms_shared_services/src/lambda_handlers/abstract/processors.py
rooms_shared_services/src/lambda_handlers/api_gateway/abstract.py
rooms_shared_services/src/lambda_handlers/api_gateway/handlers.py
rooms_shared_services/src/lambda_handlers/customer_leads/processors.py
rooms_shared_services/src/lambda_handlers/dynamodb/handlers.py
rooms_shared_services/src/lambda_handlers/dynamodb/old_handlers.py
rooms_shared_services/src/lambda_handlers/dynamodb/processors.py
rooms_shared_services/src/llms/clients/abstract.py
rooms_shared_services/src/llms/clients/poduct_source.py
rooms_shared_services/src/llms/prompts.yaml
rooms_shared_services/src/logging/http_logger.py
rooms_shared_services/src/logging/settings.py
rooms_shared_services/src/main.py
rooms_shared_services/src/models/base.py
rooms_shared_services/src/models/countries.json
rooms_shared_services/src/models/currency_rates.json
rooms_shared_services/src/models/lmbda/abstract.py
rooms_shared_services/src/models/lmbda/dynamdb_stream.py
rooms_shared_services/src/models/lmbda/http.py
rooms_shared_services/src/models/lmbda/responses.py
rooms_shared_services/src/models/products/attributes.py
rooms_shared_services/src/models/products/categories.py
rooms_shared_services/src/models/products/product_groups.py
rooms_shared_services-0.1.222.dist-info/LICENSE
rooms_shared_services-0.1.222.dist-info/METADATA
rooms_shared_services-0.1.222.dist-info/WHEEL
rooms_shared_services-0.1.222.dist-info/RECORD
