Metadata-Version: 2.1
Name: rooms-shared-services
Version: 0.1.222
Summary: 
Author: kras55
Author-email: dkras5577@gmail.com
Requires-Python: ==3.11.9
Classifier: Programming Language :: Python :: 3
Requires-Dist: aws-lambda-powertools (>=2.40.1,<3.0.0)
Requires-Dist: backoff (>=2.2.1,<3.0.0)
Requires-Dist: more-itertools (>=10.2.0,<11.0.0)
Requires-Dist: openai (>=1.35.3,<2.0.0)
Requires-Dist: pydantic (>=2.5.2,<3.0.0)
Requires-Dist: pydantic-settings (>=2.1.0,<3.0.0)
Requires-Dist: pyyaml (>=6.0.1,<7.0.0)
